package/__init__.py
package/main.py
blabla1-0.0.1.dist-info/METADATA
blabla1-0.0.1.dist-info/WHEEL
blabla1-0.0.1.dist-info/top_level.txt
blabla1-0.0.1.dist-info/RECORD
